{
    "BlueCar": {
        "checkpoints": [
            {
                "steps": 221694,
                "file_path": "results\\fase2\\BlueCar\\BlueCar-221694.onnx",
                "reward": 5774.398979187012,
                "creation_time": 1751443677.9530377,
                "auxillary_file_paths": [
                    "results\\fase2\\BlueCar\\BlueCar-221694.pt"
                ]
            }
        ],
        "final_checkpoint": {
            "steps": 221694,
            "file_path": "results\\fase2\\BlueCar.onnx",
            "reward": 5774.398979187012,
            "creation_time": 1751443677.9530377,
            "auxillary_file_paths": [
                "results\\fase2\\BlueCar\\BlueCar-221694.pt"
            ]
        }
    },
    "RedCar": {
        "checkpoints": [
            {
                "steps": 221796,
                "file_path": "results\\fase2\\RedCar\\RedCar-221796.onnx",
                "reward": null,
                "creation_time": 1751443678.2473385,
                "auxillary_file_paths": [
                    "results\\fase2\\RedCar\\RedCar-221796.pt"
                ]
            }
        ],
        "final_checkpoint": {
            "steps": 221796,
            "file_path": "results\\fase2\\RedCar.onnx",
            "reward": null,
            "creation_time": 1751443678.2473385,
            "auxillary_file_paths": [
                "results\\fase2\\RedCar\\RedCar-221796.pt"
            ]
        }
    },
    "metadata": {
        "stats_format_version": "0.3.0",
        "mlagents_version": "0.30.0",
        "torch_version": "2.2.2+cu121"
    }
}